fsspec_proxy/__init__.py
fsspec_proxy/__main__.py
fsspec_proxy/_version.py
fsspec_proxy/bytes_server.py
fsspec_proxy/cors.py
fsspec_proxy/file_manager.py
fsspec_proxy-0.1.2.dist-info/METADATA
fsspec_proxy-0.1.2.dist-info/WHEEL
fsspec_proxy-0.1.2.dist-info/entry_points.txt
fsspec_proxy-0.1.2.dist-info/licenses/LICENSE
fsspec_proxy-0.1.2.dist-info/RECORD
