Metadata-Version: 2.4
Name: fsspec-proxy
Version: 0.1.2
Dynamic: Keywords
Dynamic: Project-URL
Summary: Provide bytes to fsspec over HTTP from any backend
Author: martindurant
License: BSD 3-Clause License
License-File: LICENSE
Classifier: License :: OSI Approved :: BSD License
Classifier: Programming Language :: Python
Classifier: Programming Language :: Python :: 3
Classifier: Programming Language :: Python :: 3.9
Classifier: Programming Language :: Python :: 3.10
Classifier: Programming Language :: Python :: 3.11
Classifier: Programming Language :: Python :: 3.12
Classifier: Programming Language :: Python :: 3.13
Requires-Python: >=3.9
Requires-Dist: fastapi
Requires-Dist: fastapi-cli
Requires-Dist: fsspec>=2025.3.0
Provides-Extra: all
Requires-Dist: anaconda-cloud-storage; extra == 'all'
Requires-Dist: s3fs; extra == 'all'
Provides-Extra: anaconda
Requires-Dist: anaconda-cloud-storage; extra == 'anaconda'
Provides-Extra: s3
Requires-Dist: s3fs; extra == 's3'
